guppylang_internals/__init__.py
guppylang_internals/ast_util.py
guppylang_internals/decorator.py
guppylang_internals/diagnostic.py
guppylang_internals/dummy_decorator.py
guppylang_internals/engine.py
guppylang_internals/error.py
guppylang_internals/experimental.py
guppylang_internals/ipython_inspect.py
guppylang_internals/nodes.py
guppylang_internals/py.typed
guppylang_internals/span.py
guppylang_internals/wasm_util.py
guppylang_internals/cfg/__init__.py
guppylang_internals/cfg/analysis.py
guppylang_internals/cfg/bb.py
guppylang_internals/cfg/builder.py
guppylang_internals/cfg/cfg.py
guppylang_internals/checker/__init__.py
guppylang_internals/checker/cfg_checker.py
guppylang_internals/checker/core.py
guppylang_internals/checker/expr_checker.py
guppylang_internals/checker/func_checker.py
guppylang_internals/checker/linearity_checker.py
guppylang_internals/checker/modifier_checker.py
guppylang_internals/checker/stmt_checker.py
guppylang_internals/checker/unitary_checker.py
guppylang_internals/checker/errors/__init__.py
guppylang_internals/checker/errors/comptime_errors.py
guppylang_internals/checker/errors/generic.py
guppylang_internals/checker/errors/linearity.py
guppylang_internals/checker/errors/type_errors.py
guppylang_internals/checker/errors/wasm.py
guppylang_internals/compiler/__init__.py
guppylang_internals/compiler/cfg_compiler.py
guppylang_internals/compiler/core.py
guppylang_internals/compiler/expr_compiler.py
guppylang_internals/compiler/func_compiler.py
guppylang_internals/compiler/hugr_extension.py
guppylang_internals/compiler/modifier_compiler.py
guppylang_internals/compiler/qtm_platform_extension.py
guppylang_internals/compiler/stmt_compiler.py
guppylang_internals/definition/__init__.py
guppylang_internals/definition/common.py
guppylang_internals/definition/const.py
guppylang_internals/definition/custom.py
guppylang_internals/definition/declaration.py
guppylang_internals/definition/extern.py
guppylang_internals/definition/function.py
guppylang_internals-0.27.0.dist-info/METADATA
guppylang_internals-0.27.0.dist-info/WHEEL
guppylang_internals-0.27.0.dist-info/licenses/LICENCE
guppylang_internals-0.27.0.dist-info/RECORD
