Metadata-Version: 2.4
Name: guppylang-internals
Version: 0.27.0
Summary: Compiler internals for `guppylang` package.
Author-email: Mark Koch <mark.koch@quantinuum.com>, TKET development team <tket-support@quantinuum.com>
Maintainer-email: Mark Koch <mark.koch@quantinuum.com>, TKET development team <tket-support@quantinuum.com>
License:                                  Apache License
License-File: LICENCE
Classifier: Development Status :: 3 - Alpha
Classifier: Intended Audience :: Developers
Classifier: Intended Audience :: Science/Research
Classifier: License :: OSI Approved :: Apache Software License
Classifier: Programming Language :: Python :: 3
Classifier: Programming Language :: Python :: 3 :: Only
Classifier: Programming Language :: Python :: 3.10
Classifier: Programming Language :: Python :: 3.11
Classifier: Programming Language :: Python :: 3.12
Classifier: Programming Language :: Python :: 3.13
Classifier: Programming Language :: Python :: 3.14
Classifier: Topic :: Software Development :: Compilers
Requires-Python: <4,>=3.10
Requires-Dist: hugr~=0.15.0
Requires-Dist: tket-exts~=0.12.0
Requires-Dist: typing-extensions<5,>=4.9.0
Requires-Dist: wasmtime~=v38.0.0
Provides-Extra: pytket
Requires-Dist: pytket>=1.34; extra == 'pytket'
